[
  {
    "comment": "MOTORBOATING",
    "rate": 80085,
    "productId": "m0t0rb04t1ng8oo8s",
    "_id": "1p529i2fkqgfahu4",
    "createdAt": "2021-06-28T09:32:45.387Z"
  },
  {
    "comment": "MOTORBOATING",
    "rate": 80085,
    "productId": "m0t0rb04t1ng8oo8s",
    "_id": "1p529i6fkqgfaitq",
    "createdAt": "2021-06-28T09:32:46.669Z"
  },
  {
    "comment": "MOTORBOATING",
    "rate": 80085,
    "productId": "m0t0rb04t1ng8oo8s",
    "_id": "1p529i75kqgfajgs",
    "createdAt": "2021-06-28T09:32:47.499Z"
  },
  {
    "comment": "MOTORBOATING",
    "rate": 80085,
    "productId": "m0t0rb04t1ng8oo8s",
    "_id": "1p529i7lkqgfajzu",
    "createdAt": "2021-06-28T09:32:48.186Z"
  },
  {
    "comment": "MOTORBOATING",
    "rate": 80085,
    "productId": "m0t0rb04t1ng8oo8s",
    "_id": "1p529i7zkqgfakho",
    "createdAt": "2021-06-28T09:32:48.827Z"
  },
  {
    "comment": "MOTORBOATING",
    "rate": 80085,
    "productId": "m0t0rb04t1ng8oo8s",
    "_id": "1p529i8gkqgfakzm",
    "createdAt": "2021-06-28T09:32:49.473Z"
  },
  {
    "comment": "MOTORBOATING",
    "rate": 80085,
    "productId": "m0t0rb04t1ng8oo8s",
    "_id": "1p529i8vkqgfalha",
    "createdAt": "2021-06-28T09:32:50.109Z"
  },
  {
    "comment": "MOTORBOATING",
    "rate": 80085,
    "productId": "m0t0rb04t1ng8oo8s",
    "_id": "1p529i99kqgfammo",
    "createdAt": "2021-06-28T09:32:51.599Z"
  },
  {
    "comment": "MOTORBOATING",
    "rate": 80085,
    "productId": "m0t0rb04t1ng8oo8s",
    "_id": "1p529i9rkqgfanjv",
    "createdAt": "2021-06-28T09:32:52.794Z"
  }
]
